askmagic/__init__.py
askmagic/ask.py
askmagic-1.0.0.dist-info/METADATA
askmagic-1.0.0.dist-info/WHEEL
askmagic-1.0.0.dist-info/top_level.txt
askmagic-1.0.0.dist-info/RECORD
