Metadata-Version: 2.1
Name: askmagic
Version: 1.0.0
Summary: Eightball.
Home-page: UNKNOWN
Author: mqchinee
Author-email: UNKNOWN
License: UNKNOWN
Keywords: random,python,eightball
Platform: UNKNOWN
Classifier: Development Status :: 1 - Planning
Classifier: Intended Audience :: Developers
Classifier: Programming Language :: Python :: 3
Classifier: Operating System :: Unix
Classifier: Operating System :: MacOS :: MacOS X
Classifier: Operating System :: Microsoft :: Windows
Requires-Dist: anitrack
